yamlpars/__init__.py
yamlpars/parameters.py
yamlpars/py.typed
yamlpars/update.py
yamlpars/yaml_utils.py
yamlpars-0.4.1.dist-info/LICENSE
yamlpars-0.4.1.dist-info/METADATA
yamlpars-0.4.1.dist-info/WHEEL
yamlpars-0.4.1.dist-info/top_level.txt
yamlpars-0.4.1.dist-info/RECORD
