Metadata-Version: 2.1
Name: yamlpars
Version: 0.4.1
Summary: With yamlpars you can save configurations and parameters to YAML files, in a structured and easy-to use way.
Author: Matteo Pompili
Project-URL: Home, https://github.com/matpompili/yamlpars
Project-URL: Documentation, https://yamlpars.readthedocs.io/
Project-URL: Changelog, https://github.com/matpompili/yamlpars/blob/main/CHANGELOG.md
Classifier: Programming Language :: Python :: 3
Classifier: License :: OSI Approved :: MIT License
Classifier: Operating System :: OS Independent
Classifier: Intended Audience :: Developers
Classifier: Topic :: Software Development :: Libraries :: Python Modules
Requires-Python: >=3.8
License-File: LICENSE
Requires-Dist: addict (>=2.4.0)
Requires-Dist: ruamel.yaml (>=0.17.21)
Requires-Dist: ruamel.yaml.clib (>=0.2.6) ; python_version < "3.11" and platform_python_implementation == "CPython"
